{"nodes": [{"id": "auth_UserService", "label": "UserService", "file_type": "code", "source_file": "backend/src/main/java/com/dhara/auth/UserService.java", "source_location": null, "source_url": null, "captured_at": null, "author": null, "contributor": null}], "edges": [{"source": "auth_UserService", "target": "auth_JwtService", "relation": "calls", "confidence": "EXTRACTED", "confidence_score": 1.0, "source_file": "backend/src/main/java/com/dhara/auth/UserService.java", "source_location": null, "weight": 1.0}, {"source": "auth_UserService", "target": "auth_dto_AuthResponse", "relation": "references", "confidence": "EXTRACTED", "confidence_score": 1.0, "source_file": "backend/src/main/java/com/dhara/auth/UserService.java", "source_location": null, "weight": 1.0}, {"source": "auth_UserService", "target": "auth_dto_LoginRequest", "relation": "references", "confidence": "EXTRACTED", "confidence_score": 1.0, "source_file": "backend/src/main/java/com/dhara/auth/UserService.java", "source_location": null, "weight": 1.0}, {"source": "auth_UserService", "target": "auth_dto_RegisterRequest", "relation": "references", "confidence": "EXTRACTED", "confidence_score": 1.0, "source_file": "backend/src/main/java/com/dhara/auth/UserService.java", "source_location": null, "weight": 1.0}, {"source": "auth_UserService", "target": "auth_exception_AuthException", "relation": "references", "confidence": "EXTRACTED", "confidence_score": 1.0, "source_file": "backend/src/main/java/com/dhara/auth/UserService.java", "source_location": null, "weight": 1.0}], "hyperedges": []}