{"nodes": [{"id": "judgmentjudgmentcitation", "label": "JudgmentJudgmentCitation.java", "file_type": "code", "source_file": "backend\\src\\main\\java\\com\\dhara\\entity\\JudgmentJudgmentCitation.java", "source_location": "L1"}, {"id": "judgmentjudgmentcitation_judgmentjudgmentcitation", "label": "JudgmentJudgmentCitation", "file_type": "code", "source_file": "backend\\src\\main\\java\\com\\dhara\\entity\\JudgmentJudgmentCitation.java", "source_location": "L9"}], "edges": [{"source": "judgmentjudgmentcitation", "target": "auditableentity", "relation": "imports", "confidence": "EXTRACTED", "source_file": "backend\\src\\main\\java\\com\\dhara\\entity\\JudgmentJudgmentCitation.java", "source_location": "L3", "weight": 1.0}, {"source": "judgmentjudgmentcitation", "target": "persistence", "relation": "imports", "confidence": "EXTRACTED", "source_file": "backend\\src\\main\\java\\com\\dhara\\entity\\JudgmentJudgmentCitation.java", "source_location": "L4", "weight": 1.0}, {"source": "judgmentjudgmentcitation", "target": "getter", "relation": "imports", "confidence": "EXTRACTED", "source_file": "backend\\src\\main\\java\\com\\dhara\\entity\\JudgmentJudgmentCitation.java", "source_location": "L5", "weight": 1.0}, {"source": "judgmentjudgmentcitation", "target": "noargsconstructor", "relation": "imports", "confidence": "EXTRACTED", "source_file": "backend\\src\\main\\java\\com\\dhara\\entity\\JudgmentJudgmentCitation.java", "source_location": "L6", "weight": 1.0}, {"source": "judgmentjudgmentcitation", "target": "setter", "relation": "imports", "confidence": "EXTRACTED", "source_file": "backend\\src\\main\\java\\com\\dhara\\entity\\JudgmentJudgmentCitation.java", "source_location": "L7", "weight": 1.0}, {"source": "judgmentjudgmentcitation", "target": "judgmentjudgmentcitation_judgmentjudgmentcitation", "relation": "contains", "confidence": "EXTRACTED", "source_file": "backend\\src\\main\\java\\com\\dhara\\entity\\JudgmentJudgmentCitation.java", "source_location": "L9", "weight": 1.0}]}